pyftdi/INSTALL
pyftdi/__init__.py
pyftdi/bits.py
pyftdi/eeprom.py
pyftdi/ftdi.py
pyftdi/gpio.py
pyftdi/i2c.py
pyftdi/jtag.py
pyftdi/misc.py
pyftdi/spi.py
pyftdi/term.py
pyftdi/tracer.py
pyftdi/usbtools.py
pyftdi/doc/authors.rst
pyftdi/doc/defs.rst
pyftdi/doc/eeprom.rst
pyftdi/doc/features.rst
pyftdi/doc/gpio.rst
pyftdi/doc/index.rst
pyftdi/doc/installation.rst
pyftdi/doc/license.rst
pyftdi/doc/pinout.rst
pyftdi/doc/requirements.rst
pyftdi/doc/testing.rst
pyftdi/doc/tools.rst
pyftdi/doc/troubleshooting.rst
pyftdi/doc/urlscheme.rst
pyftdi/doc/api/eeprom.rst
pyftdi/doc/api/ftdi.rst
pyftdi/doc/api/gpio.rst
pyftdi/doc/api/i2c.rst
pyftdi/doc/api/index.rst
pyftdi/doc/api/misc.rst
pyftdi/doc/api/spi.rst
pyftdi/doc/api/uart.rst
pyftdi/doc/api/usbtools.rst
pyftdi/serialext/__init__.py
pyftdi/serialext/logger.py
pyftdi/serialext/protocol_ftdi.py
pyftdi/serialext/protocol_unix.py
pyftdi-0.57.0.data/scripts/ftconf.py
pyftdi-0.57.0.data/scripts/ftdi_urls.py
pyftdi-0.57.0.data/scripts/i2cscan.py
pyftdi-0.57.0.data/scripts/pyterm.py
pyftdi-0.57.0.dist-info/licenses/pyftdi/doc/license.rst
pyftdi-0.57.0.dist-info/METADATA
pyftdi-0.57.0.dist-info/WHEEL
pyftdi-0.57.0.dist-info/top_level.txt
pyftdi-0.57.0.dist-info/RECORD
