Metadata-Version: 2.4
Name: pyftdi
Version: 0.57.0
Summary: FTDI device driver (pure Python)
Home-page: http://github.com/eblot/pyftdi
Author: Emmanuel Blot
Author-email: emmanuel.blot@free.fr
Maintainer: Emmanuel Blot
Maintainer-email: emmanuel.blot@free.fr
License: BSD-3-Clause
Keywords: driver,ftdi,usb,serial,spi,i2c,twi,rs232,gpio,bit-bang
Classifier: Development Status :: 4 - Beta
Classifier: Environment :: Other Environment
Classifier: Natural Language :: English
Classifier: Intended Audience :: Developers
Classifier: Operating System :: MacOS :: MacOS X
Classifier: Operating System :: POSIX
Classifier: Programming Language :: Python :: 3.9
Classifier: Programming Language :: Python :: 3.10
Classifier: Programming Language :: Python :: 3.11
Classifier: Programming Language :: Python :: 3.12
Classifier: Programming Language :: Python :: 3.13
Classifier: Topic :: Software Development :: Libraries :: Python Modules
Classifier: Topic :: System :: Hardware :: Hardware Drivers
Requires-Python: >=3.9
License-File: pyftdi/doc/license.rst
Requires-Dist: pyusb!=1.2.0,>=1.0.0
Requires-Dist: pyserial>=3.0
Dynamic: author
Dynamic: author-email
Dynamic: classifier
Dynamic: description
Dynamic: description-content-type
Dynamic: home-page
Dynamic: keywords
Dynamic: license
Dynamic: license-file
Dynamic: maintainer
Dynamic: maintainer-email
Dynamic: requires-dist
Dynamic: requires-python
Dynamic: summary
